MANIFEST.in
README.md
setup.py
takeaway/__init__.py
takeaway/command_line.py
takeaway/interface.py
takeaway/main.py
takeaway/parser.py
takeaway.egg-info/PKG-INFO
takeaway.egg-info/SOURCES.txt
takeaway.egg-info/dependency_links.txt
takeaway.egg-info/entry_points.txt
takeaway.egg-info/not-zip-safe
takeaway.egg-info/requires.txt
takeaway.egg-info/top_level.txt
takeaway/basket/__init__.py
takeaway/basket/basket.py
takeaway/basket/error.py
takeaway/database/__init__.py
takeaway/database/database.py
takeaway/database/declarative.py
takeaway/database/error.py
takeaway/scrapper/__init__.py
takeaway/scrapper/basic.py
takeaway/scrapper/de.py
takeaway/scrapper/error.py
takeaway/scrapper/output.py
takeaway/scrapper/request.py
takeaway/scrapper/scrapper.py
takeaway/scrapper/vietnamm.py
takeaway/user/__init__.py
takeaway/user/error.py
takeaway/user/user.py