Metadata-Version: 1.0
Name: takeaway
Version: 0.2.0
Summary: Command line interface for takeaway.com websites
Home-page: https://github.com/Ovvovy/TakeAway
Author: Ovv
Author-email: ovv@outlook.com
License: MIT
Platform: UNKNOWN
